{
  "appPageId" : "d7230d24-3471-4f44-946c-1747d67daa79",
  "componentName" : "siteforce:sldsOneColLayout",
  "dataProviders" : [ ],
  "id" : "7a211088-53db-44bf-96a6-4cecb1fcb1f2",
  "label" : "Record Detail",
  "regions" : [ {
    "id" : "2fda5535-d425-4a09-b9f3-75a72d30f2e0",
    "regionName" : "header",
    "type" : "region"
  }, {
    "components" : [ {
      "componentAttributes" : {
        "recordId" : "{!recordId}"
      },
      "componentName" : "forceCommunity:recordHeadline",
      "id" : "c3329736-d639-4b8a-987c-344e4afe64f2",
      "renderPriority" : "NEUTRAL",
      "renditionMap" : { },
      "type" : "component"
    }, {
      "componentAttributes" : {
        "detailsTabLabel" : "Details",
        "discussionsTabLabel" : "Feed",
        "recordId" : "{!recordId}",
        "relatedTabLabel" : "Related",
        "showLegacyActivityComposer" : false,
        "tab1Type" : "details",
        "tab2Type" : "related",
        "tab3Type" : "chatter",
        "tab4Type" : "none",
        "timelineTabLabel" : "Activity"
      },
      "componentName" : "forceCommunity:recordHomeTabs",
      "id" : "2185e756-9fe2-4296-9b31-2e2bed5c9c2e",
      "renderPriority" : "NEUTRAL",
      "renditionMap" : { },
      "type" : "component"
    } ],
    "id" : "db7ff754-8c65-4977-a39b-65918a5795f5",
    "regionName" : "content",
    "type" : "region"
  }, {
    "id" : "7a422412-8495-4fa5-9b5b-287ec194dc12",
    "regionName" : "footer",
    "type" : "region"
  }, {
    "components" : [ {
      "componentAttributes" : {
        "customHeadTags" : "",
        "description" : "",
        "title" : "{!Record._Object}: {!Record._Title}"
      },
      "componentName" : "forceCommunity:seoAssistant",
      "id" : "0c7216ad-b2cd-4bc8-9969-9cb99aec14bf",
      "renditionMap" : { },
      "type" : "component"
    } ],
    "id" : "eb3b0fa4-b807-40ac-bcc6-ec41e8fa98d4",
    "regionName" : "sfdcHiddenRegion",
    "type" : "region"
  } ],
  "themeLayoutType" : "Inner",
  "type" : "view",
  "viewType" : "detail"
}